testypie/__init__.py
testypie/_version.py
testypie/py.typed
testypie-1.2.2.dist-info/LICENCE.md
testypie-1.2.2.dist-info/LICENSE.md
testypie-1.2.2.dist-info/METADATA
testypie-1.2.2.dist-info/WHEEL
testypie-1.2.2.dist-info/entry_points.txt
testypie-1.2.2.dist-info/top_level.txt
testypie-1.2.2.dist-info/RECORD
