Metadata-Version: 2.1
Name: testypie
Version: 1.2.2
Summary: HTTP proxy that generates and loads from fixtures for testing.
Home-page: https://github.com/avengerpenguin/testypie
Author: Ross Fenning
Author-email: github@rossfenning.co.uk
License: GPLv3+
Platform: UNKNOWN
Classifier: License :: OSI Approved :: GNU General Public License v3 or later (GPLv3+)
Classifier: Operating System :: OS Independent
Classifier: Programming Language :: Python
Requires-Dist: Flask
Requires-Dist: requests
Requires-Dist: httplib2
Requires-Dist: PyYAML
Requires-Dist: clize
Provides-Extra: test
Requires-Dist: pytest ; extra == 'test'
Requires-Dist: pytest-mypy ; extra == 'test'
Requires-Dist: pytest-pikachu ; extra == 'test'
Requires-Dist: types-requests ; extra == 'test'
Requires-Dist: types-Flask ; extra == 'test'
Requires-Dist: types-PyYAML ; extra == 'test'
Requires-Dist: types-Werkzeug ; extra == 'test'
